{
  "name": "Wesley Simmons",
  "age": 64,
  "address": {
    "street": "Sodo Avenue",
    "city": "Seuware",
    "state": "FL",
    "zip": "55121"
  },
  "contact": {
    "phone": "(453) 972-1125",
    "servicePhone": "800365552"
  },
  "birthday": "1965-10-03T04:09:43.842Z",
  "ip": "66.11.129.139",
  "foo": "bar",
  "profile": {
    "about": "To ze kurdobav feku paj fi po ozvajih paktuzza afealebam gezvostah zutucic fug reh bupmuk dilare rivde. Cavvu wouh efizek ad cibem olo ofpubnep edakidac kupa tuute odoj fal zihafo. Mev oro sutomdec agof sofahga votci udkomi vipoj rug vuwu uju golag muz. Henu donimasep evujuwus omegeg paigacaj zakmenug buf neuz ves jevo reazota ni te ep gutpuha ha huc. Vu nigmum os oniibfoc gavo zuubtec ticeafe emnapjav iba tisugojat bu feh ope lenife daw.",
    "bio": "Innemad wozok hurjemhuw edisewo nafrecun cis hosinban puw pojwe apkov nevo rareva. Milweg jakeuh vik jojubi ninu new je viz ufagitaw saufen gapizroj guniul voeki. Pej pe bemga lobes lu ri ricujojij tu har zefuzet wuolnaz lub jucwupnot japo lat osduv ofcuese. Deli soice kef avha lib erhepi uvbif bi iwokatjir kun katoobo gojuje ak rambe goraupe eh. Odutatweg ba ja jot puzezafov ahdol vo ji vec doj mi fesvobba maud ra vu. Vihwezak lu ov buwo iga fuzpuzwo lasoup enna esbativ biinsil wol mugbufeh uta ocekojo duzas hazcof god."
  },
  "apiKey": "10d5233479f44f277dde3a00a0d4f71e3842a5100dd13d4ca1abcbe06df5946d",
  "currency": {
    "code": "UZS",
    "name": "Uzbekistan Som"
  }
}