{
  "name": "Isaac Rodriguez",
  "age": 61,
  "address": {
    "street": "Derib Key",
    "city": "Sajwananu",
    "state": "OR",
    "zip": "64826"
  },
  "contact": {
    "phone": "(388) 943-3741",
    "servicePhone": "800948489"
  },
  "birthday": "1959-01-05T11:18:45.354Z",
  "ip": "60.209.70.150",
  "foo": "bar",
  "profile": {
    "about": "Mor tinedu ciw dafittej nip pop kuodape ner coh tuvibbo ota va mefladi. Ke ovuowkef luv hegupzim noetfuh dom jijug joriwkas mamow fuga pesu zuhkoj. Fes icri maddegut mo lob malannam wesfi lucu nu tocne das ike bogur. Wegzuta biebiid bac zec huuwoho lisuj roesofi ako hocbovred ovazek ojowazwu razic ikopah bubhov huckurfeg seobala nalezosi.",
    "bio": "Lijgi jaoj ihehefum ocuiti efze nolawoore zusalzit cof pi giwru penanciw pa tazat ib nufiwo. Vazej wek vijno doduti rofaceme ig timizma dod po lika zuc nana ej zop mumbeor or. Dobuhaj wah ote jaena nokok wimo mum roh ih fedobtu irgiv huvwik li ak azotak lodfirpen uz. Sisu pumaveuj buzi febodu rotgagzu wihaaj lezpuh awiafoli dimdusir tetakid ivo gofciiz wu nupoki ividehzi zileb coul pol. Ucu tovilan vagjihgo etegud cuwad samaz sos jemkol mihek libsomma mucioci ho gevek lowok hugov nijpov. Vibvisa fu wa fiwmereh pof di bi sitrus fijwi rosegi hisuto mujecud vommijivu. Tot toude bof caj lakpa cacni ovu pok jizjuvzu zevfuco ratdiw jidafidi go bo ihimib izvuzzu."
  },
  "apiKey": "a1956721298fa70a48ba2b0e28aba2d2362a5d1f27784a083fd0360d447aade6",
  "currency": {
    "code": "JOD",
    "name": "Jordan Dinar"
  }
}